coldtype/__init__.py
coldtype/__main__.py
coldtype/axidraw.py
coldtype/beziers.py
coldtype/css.py
coldtype/drawbot.py
coldtype/helpers.py
coldtype/osutil.py
coldtype/random.py
coldtype/raster.py
coldtype/skiashim.py
coldtype/test.py
coldtype/tool.py
coldtype/warping.py
coldtype/assets/glyphNamesToUnicode.txt
coldtype/blender/__init__.py
coldtype/blender/fluent.py
coldtype/blender/livepreview.py
coldtype/blender/panel3d.py
coldtype/blender/render.py
coldtype/blender/timedtext.py
coldtype/blender/util.py
coldtype/blender/watch.py
coldtype/capture/__init__.py
coldtype/color/__init__.py
coldtype/color/html.py
coldtype/demo/ColdtypeObviously-VF.ttf
coldtype/demo/JetBrainsMono.ttf
coldtype/demo/MutatorSans.ttf
coldtype/demo/RecMono-CasualItalic.ttf
coldtype/demo/blank.py
coldtype/demo/boiler.py
coldtype/demo/boiler_renderable.py
coldtype/demo/demo.py
coldtype/demo/docstrings.py
coldtype/demo/gifski.py
coldtype/demo/glfw34.py
coldtype/demo/glyphloop.py
coldtype/demo/glyphs.py
coldtype/demo/instances.py
coldtype/demo/midi.py
coldtype/demo/midicc.py
coldtype/demo/transparency_appicon.png
coldtype/demo/transparency_blocks.png
coldtype/demo/vf.py
coldtype/demo/viewseq.py
coldtype/fx/chainable.py
coldtype/fx/diagram.py
coldtype/fx/motion.py
coldtype/fx/shapes.py
coldtype/fx/skia.py
coldtype/fx/warping.py
coldtype/fx/xray.py
coldtype/geometry/__init__.py
coldtype/geometry/atom.py
coldtype/geometry/curve.py
coldtype/geometry/edge.py
coldtype/geometry/geometrical.py
coldtype/geometry/line.py
coldtype/geometry/point.py
coldtype/geometry/primitives.py
coldtype/geometry/rect.py
coldtype/grid/__init__.py
coldtype/img/abstract.py
coldtype/img/blendmode.py
coldtype/img/drawbotimage.py
coldtype/img/skiaimage.py
coldtype/img/skiasvg.py
coldtype/interpolation/__init__.py
coldtype/midi/controllers.py
coldtype/notebook/__init__.py
coldtype/notebook/parser.py
coldtype/pens/axidrawpen.py
coldtype/pens/blenderpen.py
coldtype/pens/drawablepen.py
coldtype/pens/drawbotpen.py
coldtype-0.12.2.dist-info/METADATA
coldtype-0.12.2.dist-info/WHEEL
coldtype-0.12.2.dist-info/entry_points.txt
coldtype-0.12.2.dist-info/top_level.txt
coldtype-0.12.2.dist-info/RECORD
