Metadata-Version: 2.4
Name: coldtype
Version: 0.12.2
Summary: Functions for manual vectorized typesetting.
Author-email: Rob Stenson <rob.stenson@gmail.com>
Project-URL: Homepage, https://coldtype.xyz
Project-URL: Documentation, https://coldtype.goodhertz.com
Project-URL: Repository, https://github.com/coldtype/coldtype
Project-URL: Issues, https://github.com/coldtype/coldtype/issues
Project-URL: Changelog, https://github.com/coldtype/coldtype/blob/main/CHANGELOG.md
Requires-Python: >=3.11
Requires-Dist: fontPens==0.2.4
Requires-Dist: easing-functions==1.0.4
Requires-Dist: b3denv>=0.0.12
Requires-Dist: coldtype-fontgoggles==1.8.4.7
Requires-Dist: skia-pathops
Requires-Dist: defcon>=0.12.0
Requires-Dist: uharfbuzz<0.47.0
Provides-Extra: more-fonts
Requires-Dist: ufo2ft>=3.2.8; extra == "more-fonts"
Requires-Dist: coldtype-fontgoggles[more-fonts]==1.8.4.7; extra == "more-fonts"
Provides-Extra: viewer
Requires-Dist: glfw; extra == "viewer"
Requires-Dist: PyOpenGL; extra == "viewer"
Requires-Dist: skia-python; extra == "viewer"
Requires-Dist: skia-pathops; extra == "viewer"
Requires-Dist: numpy; extra == "viewer"
Requires-Dist: potracer; extra == "viewer"
Requires-Dist: requests; extra == "viewer"
Requires-Dist: mido; extra == "viewer"
Requires-Dist: ufo2ft>=3.2.8; extra == "viewer"
Requires-Dist: coldtype-fontgoggles[more-fonts]==1.8.4.7; extra == "viewer"
Provides-Extra: drawbot
Requires-Dist: numpy; extra == "drawbot"
Provides-Extra: unicode
Requires-Dist: unicodedata2; extra == "unicode"
Provides-Extra: notebook
Requires-Dist: skia-pathops; extra == "notebook"
Requires-Dist: skia-python; extra == "notebook"
Requires-Dist: potracer; extra == "notebook"
Requires-Dist: tdqm; extra == "notebook"
Provides-Extra: audio
Requires-Dist: pyaudio; extra == "audio"
Requires-Dist: soundfile; extra == "audio"
Provides-Extra: website
Requires-Dist: jinja2; extra == "website"
Requires-Dist: python-frontmatter; extra == "website"
Requires-Dist: livereload; extra == "website"
Requires-Dist: Markdown; extra == "website"
Requires-Dist: markdown-captions; extra == "website"
Requires-Dist: beautifulsoup4; extra == "website"
Requires-Dist: brotli; extra == "website"
Requires-Dist: lxml; extra == "website"
Requires-Dist: pygments; extra == "website"
Requires-Dist: sourcetypes; extra == "website"
Requires-Dist: favicons; extra == "website"
